clelandlab_quick-0.6.10.dist-info/licenses/LICENSE
quick/VERSION
quick/__init__.py
quick/auto.py
quick/experiment.py
quick/experiment.yml
quick/helper.py
quick/mercator.py
clelandlab_quick-0.6.10.dist-info/METADATA
clelandlab_quick-0.6.10.dist-info/WHEEL
clelandlab_quick-0.6.10.dist-info/top_level.txt
clelandlab_quick-0.6.10.dist-info/RECORD
