Metadata-Version: 2.4
Name: clelandlab-quick
Version: 0.6.10
Summary: QuICK is a universal wrap of QICK.
Home-page: https://github.com/clelandlab/quick
Author: Cleland Lab
Author-email: clelandlab@proton.me
Project-URL: Source, https://github.com/clelandlab/quick
Project-URL: Documentation, https://clelandlab-quick.readthedocs.io/en/latest/
Project-URL: Tracker, https://github.com/clelandlab/quick/issues
Keywords: QICK,quantum,experiment,measurement,qubit,control,readout,fpga
Classifier: Development Status :: 3 - Alpha
Classifier: Intended Audience :: Developers
Classifier: Topic :: Software Development :: Build Tools
Classifier: License :: OSI Approved :: MIT License
Classifier: Programming Language :: Python :: 3
Classifier: Programming Language :: Python :: 3.8
Classifier: Programming Language :: Python :: 3.9
Classifier: Programming Language :: Python :: 3.10
Classifier: Programming Language :: Python :: 3.11
Classifier: Programming Language :: Python :: 3.12
Classifier: Programming Language :: Python :: 3 :: Only
Requires-Python: >=3.8, <4
License-File: LICENSE
Requires-Dist: qick==0.2.366
Requires-Dist: numpy
Requires-Dist: scipy
Requires-Dist: pyyaml
Requires-Dist: pyro4
Requires-Dist: matplotlib
Requires-Dist: ipython
Dynamic: author
Dynamic: author-email
Dynamic: classifier
Dynamic: description
Dynamic: description-content-type
Dynamic: home-page
Dynamic: keywords
Dynamic: license-file
Dynamic: project-url
Dynamic: requires-dist
Dynamic: requires-python
Dynamic: summary
